{"51000":["México","Villa de Allende",["Cabecera de Indígenas","San José Villa de Allende"]],"51004":["México","Villa de Allende",["Vare Chiquichuca","Batán Chico","Casa Blanca","Manzana del Puerto","Los Hoyos"]],"51005":["México","Villa de Allende",["San Pablo Malacatepec","Santa Teresa","La Peña","Ampliación Ejido de San Ildefonso","Mesa Chica","Loma Chica","Loma de San Pablo"]],"51006":["México","Villa de Allende",["San Juan","Manzana los Colchones"]],"51007":["México","Villa de Allende",["San Jerónimo Totoltepec","El Aventurero","Chiquichuca","El Chirimoyo","Mesas de San Jerónimo","El Potrero","Santa Cruz, San Jerónimo Totoltepec"]],"51008":["México","Villa de Allende",["San Ildefonso","Manzana de Cashte"]],"51009":["México","Villa de Allende",["De San Miguel","Barrio de Santiago","Santa María de las Delicias"]],"51010":["México","Villa de Allende",["Los Cedros","Loma de Juárez"]],"51013":["México","Villa de Allende",["San Francisco de Asís","El Boncho","La Joya"]],"51014":["México","Villa de Allende",["El Salto","Los Tules"]],"51015":["México","Villa de Allende",["El Jacal","Salitre del Cerro","San Isidro","Soledad del Salitre"]],"51016":["México","Villa de Allende",["Buenavista 23","Bosencheve","Las Dalias","El Cinco","Manzana de Chichicaishle","Los Pozos","Las Casitas"]],"51017":["México","Villa de Allende",["Santa Cruz","San Miguel la Máquina"]],"51019":["México","Villa de Allende",["Cuesta del Carmen","La Piedra","San Juan Buenavista","El Puerto Lengua de Vaca","Macia","Mesas de San Juan Buenavista","Mesas del Clarín"]],"51020":["México","Villa de Allende",["San Felipe Santiago"]],"51024":["México","Villa de Allende",["Mesas de Zacango","San Cayetano","Monte Alto"]],"51025":["México","Villa de Allende",["Sabana del Rosario","Mesas de San Martín"]],"51026":["México","Villa de Allende",["Sabana de Taborda 1ra. Sección","Sabana de San Jerónimo","Sabana de Taborda 2da. Sección"]],"51027":["México","Villa de Allende",["Cerro de Guadalupe","San Martín","Morelos","La Sabana de San Jerónimo","Sabana de la Peña"]],"51028":["México","Villa de Allende",["Sabana del Madroño","Sabana del Refugio","Filiberto Gómez"]],"51029":["México","Villa de Allende",["Los Berros","Manzana la Pera","San Agustín Berros el Salto"]],"51030":["México","Donato Guerra",["Cabecera de Indígenas Segundo Cuartel","Cabecera de Indígenas Primer Cuartel","Villa Donato Guerra","San Agustín de las Palmas (San Agustín)"]],"51034":["México","Donato Guerra",["San Lucas Texcaltitlán"]],"51035":["México","Donato Guerra",["San Lucas Texcaltitlán (Sabanillas)","Santiago Huitlapaltepec"]],"51036":["México","Donato Guerra",["San José Tilostoc"]],"51040":["México","Donato Guerra",["San Simón de la Laguna"]],"51043":["México","Donato Guerra",["San Antonio de la Laguna"]],"51044":["México","Donato Guerra",["San Martín Obispo","San Martín Obispo (San Martín San Pedro)","San Antonio Hidalgo (Ranchería de San Antonio)","Puerto de la Cruz"]],"51045":["México","Donato Guerra",["Batán Chico","Batán Grande"]],"51046":["México","Donato Guerra",["San Francisco Mihualtepec","San Miguel Xooltepec"]],"51050":["México","Donato Guerra",["San Juan Xoconusco","De Arriba de San Juan Xoconusco"]],"51054":["México","Donato Guerra",["Mesas Altas de Xoconusco"]],"51055":["México","Donato Guerra",["Macheros","Hacienda las Galeras (Galeras)","Llano Redondo de Zaragoza (Llano Redondo)","El Capulín","La Fundición"]],"51070":["México","Ixtapan del Oro",["La Calzada","Ixtapan del Oro","San Martín Ocoxochitepec (San Martín)"]],"51074":["México","Ixtapan del Oro",["San Miguel Ixtapan"]],"51075":["México","Ixtapan del Oro",["La Mesa de San Martín","El Teperreal"]],"51076":["México","Ixtapan del Oro",["Miahuatlán de Hidalgo (Santa Cruz Miahuatlán)"]],"51077":["México","Ixtapan del Oro",["Miahuatlán"]],"51080":["México","Ixtapan del Oro",["El Chilar","Ayalita"]],"51083":["México","Ixtapan del Oro",["La Puerta"]],"51084":["México","Ixtapan del Oro",["Peña Colorada","La Calera de los Gallos","Milpillas"]],"51085":["México","Ixtapan del Oro",["Tutuapan"]],"51089":["México","Ixtapan del Oro",["San Telmo","Santa Cruz Viejo"]],"51100":["México","Santo Tomás",["Santo Tomás de los Plátanos"]],"51104":["México","Santo Tomás",["San Miguel Sandemialma","Ojo de Agua"]],"51105":["México","Santo Tomás",["Los Nogales","El Sifón","Rincón Chico","Rincón Grande","Rincón Vivero (El Maracaná)","Frontón Vivero"]],"51106":["México","Santo Tomás",["El Salitre Bramador","Tacuitapan","Salitre Terreros","San Pedro Ixtapantongo (Ixtapantongo)","Loma Bonita","Las Fincas","Las Canoas"]],"51108":["México","Santo Tomás",["Santa Bárbara","Viejo"]],"51109":["México","Santo Tomás",["El Plan","El Llano"]],"51115":["México","Santo Tomás",["Poblado de Santo Tomás (El Puerto San Isidro)","Potrero de Abajo (Colonia Guadalupe)","El Anono","Potrero de Abajo (Granadillo)"]],"51116":["México","Santo Tomás",["San Pedro el Grande","San José Barbechos (Los Barbechos)"]],"51117":["México","Santo Tomás",["Salitre de la Cal (El Zapote)","Potrero de Arriba (La Ceiba)"]],"51130":["México","Otzoloapan",["Otzoloapan"]],"51136":["México","Otzoloapan",["Estancia Chica"]],"51137":["México","Otzoloapan",["Agua Zarca (Agua Zarca de Arriba)"]],"51138":["México","Otzoloapan",["El Calvario (San José el Calvario)"]],"51139":["México","Otzoloapan",["Pinal del Marquesado"]],"51140":["México","Otzoloapan",["San Miguel Piru (El Piru)","San Miguel de la Campana (San Miguel)"]],"51144":["México","Otzoloapan",["Terreros"]],"51145":["México","Otzoloapan",["Guadalupe (Los Lotes)"]],"51147":["México","Otzoloapan",["El Limón"]],"51149":["México","Otzoloapan",["Zuluapan"]],"51160":["México","Zacazonapan",["Alcantarilla","Zacazonapan","Juan Villafaña"]],"51163":["México","Zacazonapan",["Santa María"]],"51164":["México","Zacazonapan",["El Potrero"]],"51170":["México","Zacazonapan",["Arrastradero"]],"51173":["México","Zacazonapan",["La Cañada","El Puerto"]],"51200":["México","Valle de Bravo",["San Antonio","Manguito","Agua Fría","El Calvario","ISSEMYM","La Peña","Sánchez","Emiliano Zapata","Loma Bonita","La Capilla","Barranca Seca","De Guadalupe","Avándaro","Los Saucos","Valle de Bravo","Rincón Villa del Valle","Otumba","Santa María Ahuacatlan","Monte Alto"]],"51206":["México","Valle de Bravo",["La Boquilla (Cerro el Cualtenco la Boquilla)","IZAR","El Cerrillo (San José el Cerrillo)"]],"51207":["México","Valle de Bravo",["Tres Puentes","San Mateo Acatitlán","El Castellano","Loma de Rodríguez","Loma de Chihuahua","Rincón de Estradas"]],"51208":["México","Valle de Bravo",["La Candelaria"]],"51209":["México","Valle de Bravo",["Santa María Pipioltepec (Pipioltepec)"]],"51210":["México","Valle de Bravo",["Santa Teresa Tiloxtoc"]],"51216":["México","Valle de Bravo",["El Aguacate"]],"51217":["México","Valle de Bravo",["El Arco","San Gaspar el Lago","San Antonio","San Gaspar"]],"51218":["México","Valle de Bravo",["Santa Magdalena Tiloxtoc"]],"51219":["México","Valle de Bravo",["San Gabriel Ixtla"]],"51220":["México","Valle de Bravo",["Cerro Colorado","El Fresno (El Fresno la Compañía)","La Volanta"]],"51225":["México","Valle de Bravo",["Cuadrilla de Dolores"]],"51226":["México","Valle de Bravo",["Valle Escondido","Escalerillas","Casas Viejas","Peña Blanca"]],"51229":["México","Valle de Bravo",["Mesa de Jaimes"]],"51230":["México","Valle de Bravo",["Loma Bonita","Colorines","San Juan Atezcapan","San Nicolás Tolentino","El Durazno","El Polvorin"]],"51236":["México","Valle de Bravo",["Los Pozos (Pinar de Osorios)"]],"51237":["México","Valle de Bravo",["El Manzano"]],"51238":["México","Valle de Bravo",["La Huerta San Agustín","Mesa Rica (La Finca)","San José Potrerillos (Potrerillos)"]],"51239":["México","Valle de Bravo",["Cerro Gordo"]],"51240":["México","Valle de Bravo",["San Simón el Alto"]],"51245":["México","Valle de Bravo",["Tehuastepec (San José Tehuastepec)","Godínez Tehuastepec"]],"51246":["México","Valle de Bravo",["Mesa de Dolores (Mesa de Dolores Segunda Sección)","Mesa de Dolores Primera Sección (Mesa del Rayo)","Atesquelites (Tres Quelites)"]],"51247":["México","Valle de Bravo",["Santo Tomás el Pedregal","La Laguna","Tierra Grande (La Loma)"]],"51248":["México","Valle de Bravo",["Rancho Avándaro Country Club","La Palma","Tenantongo"]],"51260":["México","Amanalco",["San Jerónimo Primera Sección (El Convento)","Amanalco de Becerra","San Jerónimo","San Juan"]],"51265":["México","Amanalco",["Rincón de Guadalupe","San Lucas"]],"51266":["México","Amanalco",["Las Pilas","San Mateo","San Miguel (San Miguel Tenextepec)","San Sebastián el Chico","Pueblo Nuevo"]],"51267":["México","Amanalco",["San Mateo Quinta Sección (La Providencia)","San Sebastián el Grande"]],"51268":["México","Amanalco",["Polvillos (San Bartolo Quinta Sección)","San Bartolo"]],"51270":["México","Amanalco",["El Ancón","El Temporal"]],"51273":["México","Amanalco",["Capilla Vieja","Ojo de Agua"]],"51274":["México","Amanalco",["Corral de Piedra"]],"51280":["México","Amanalco",["El Capulín Segunda Sección","El Capulín Tercera Sección (Palo Mancornado)","Huacal Viejo","El Capulín Primera Sección","Agua Bendita"]],"51285":["México","Amanalco",["El Potrero Segunda Sección","El Potrero"]],"51287":["México","Amanalco",["Hacienda Nueva","El Zacatonal","San Lucas Cuarta Sección (San Francisco)","El Pedregal"]],"51300":["México","Temascaltepec",["La Cascada (Barrio del Varal)","La Magdalena (La Magdalena)","San Francisco","Balveria","San Sebastián Carboneras (Carboneras)","Temascaltepec de González","Del Fortín","Milán","De Santiago","Del Temeroso","De Cantarranas","Carnicería"]],"51303":["México","Temascaltepec",["San Lucas del Pulque"]],"51304":["México","Temascaltepec",["Telpintla","La Albarrada (San Francisco la Albarrada)","Los Timbres","El Tule"]],"51305":["México","Temascaltepec",["El Cerro Pelón","El Peñón"]],"51310":["México","Temascaltepec",["La Finca","El Salitre"]],"51314":["México","Temascaltepec",["El Chilar del Ejido de las Trancas","Las Trancas","San Pedro Tenayac","Potrero de Tenayac"]],"51315":["México","Temascaltepec",["Lampazos"]],"51320":["México","Temascaltepec",["San Mateo Almomoloa","Potrero de San José (La Rinconada)"]],"51323":["México","Temascaltepec",["San Francisco Oxtotilpan","Mesón Viejo"]],"51324":["México","Temascaltepec",["Hoyos de Vázquez","San Miguel Oxtotilpan"]],"51325":["México","Temascaltepec",["Granjas de Cieneguillas","Santanas","La Comunidad","Cieneguillas de González (Cieneguillas)","San Antonio Albarranes"]],"51326":["México","Temascaltepec",["Jesús del Monte"]],"51340":["México","Temascaltepec",["Real de Arriba","Rincón de San Andrés","Mina del Rincón","Las Mesas de Real de Arriba","San Andrés de los Gama","Milpas Viejas"]],"51344":["México","Temascaltepec",["La Laguna","Los Ocotes","Pedregales de Tequesquipan","Pueblo Nuevo","San Martín Tequesquipan (Tequesquipan)","La Estancia de Tequesquipan","Rincón de Atarasquillo","Rincón de Tequesquipan","San Juan"]],"51345":["México","Temascaltepec",["El Varal","Las Lágrimas"]],"51346":["México","Temascaltepec",["Cajones","Cieneguillas de Labra","Labor las Cabras","Manzana de Tequesquipan (Las Manzanas)","Manzana del Jabalí","La Cumbre","La Guacamaya","Plan de Vigas"]],"51350":["México","Zinacantepec",["San Miguel Zinacantepec Centro"]],"51353":["México","Zinacantepec",["Los Rosales"]],"51354":["México","Zinacantepec",["La Joya","Ejidal San Francisco Tlalcilalcalpan","De San Miguel","Del Calvario","La Esperanza","Cerro del Murciélago","Las Ánimas","La Aurora II","La Aurora I","Residencial Zinacantepec","23 de Octubre","Los Maestros","Villas de Guadalupe","Residencial San Miguel","Vistas al Nevado"]],"51355":["México","Zinacantepec",["San Valentín","El Capón (Puerta del Llano)","Santa Martha","Idílica Reserva Serratón","IDÍLICA Serratón","Las Flores Residencial","Zimbrones","Las Culturas","Emiliano Zapata","San Jorge","Residencial La Victoria","Rinconada de Tecaxic","Zamarrero","San Lorenzo Cuautenco","San Luis Mextepec","Rancho San Nicolás","Bosques Residencial","Ojuelos","La Virgen","La Joya","El Porvenir","La Loma","Casa Grande","Privadas de la Hacienda","Nueva Serratón","Zimbron","Vista Hermosa"]],"51356":["México","Zinacantepec",["De la Veracruz","San Gregorio","Irma Patricia Galindo de Rez","Deportiva","Lindavista"]],"51357":["México","Zinacantepec",["San Matías Transfiguración","El Testerazo","Ricardo Flores Magón","Hacienda San José Barbabosa","El Potrero Barbosa","Paraje la Puerta de Barbabosa","Vista Nevado Plus"]],"51360":["México","Zinacantepec",["Santa María del Monte"]],"51364":["México","Zinacantepec",["El Cóporo","El Curtidor","San Miguel Hojas Anchas"]],"51366":["México","Zinacantepec",["San Bartolo del Llano (San Isidro)","San Bartolo el Viejo"]],"51367":["México","Zinacantepec",["Loma del Kiosco","San Cristóbal Tecolit","Loma de San Francisco","De México"]],"51370":["México","Zinacantepec",["Bosques del Nevado","San Juan de las Huertas","Santa Cruz Cuauhtenco","Morelos","Dos de Marzo"]],"51373":["México","Zinacantepec",["Recibitas (El Remolino)"]],"51374":["México","Zinacantepec",["Ojo de Agua"]],"51375":["México","Zinacantepec",["Tejalpa","Benito Juárez"]],"51380":["México","Zinacantepec",["La Cruz","San Antonio Acahualco"]],"51383":["México","Zinacantepec",["Cuauhtémoc","Progreso","San Pedro Tejalpa"]],"51384":["México","Zinacantepec",["El Contadero de Matamoros (San José)"]],"51385":["México","Zinacantepec",["Ciendabajo (Hacienda de Abajo)"]],"51386":["México","Zinacantepec",["La Cañada (Cañada Grande)","La Herradura"]],"51390":["México","Zinacantepec",["La Puerta del Monte","Buenavista"]],"51393":["México","Zinacantepec",["Loma Alta","Raíces","La Peñuela"]],"51400":["México","Tejupilco",["Tejupilco de Hidalgo Centro","La Isla","Sánchez","Hidalgo","La Florida"]],"51410":["México","Tejupilco",["Rincón de Ugarte","Jalpan (Jalpan San Simón)","San José de la Laguna","Agua Bendita","Buenavista Primera Sección","Cerro de Cacalotepec (Cacalotepec)","El Cuagüilote Ojo de Agua (La Pera)","Ojo de Agua (Rincón de Ugarte)","Rincón de López"]],"51412":["México","Tejupilco",["Rincón del Carmen","Juárez","Lomas de Tejupilco","México 68","Rincón de Jaimes","Juntas de Zacatepec (El Pedregal Segunda Manzana)","Rincón de Aguirre","Santo Domingo-Zacatepec","Vicente Guerrero","Luis Donaldo Colosio","Las Américas","Independencia","Cerro de Mazatepec","El Ocote","La Laguna de Mazatepec","Mazatepec","Rinconada de la Labor","Río de Aquiagua (Aquiagua)","Del Sol","Emiliano Zapata","Las Rosas"]],"51413":["México","Tejupilco",["San Andrés Ocotepec","San Gabriel Pantoja","Los Baños","Plan de Maguey","Puerto Madroño","Rincón de San Gabriel"]],"51414":["México","Tejupilco",["La Cabecera (Cabecera de los Arrayanes)","Paso de Vigas","Cuadrilla de Leones","Los Pericones","Rincón del Naranjo (La Cabecera)","Los Colorines","Fragüita"]],"51415":["México","Tejupilco",["El Capire","El Calvario","Cañadas de San Simón (Cañada de Chivas)","Epazotes","Jumiltepec","Suquitila","El Cirián de la Laguna (El Cirián)"]],"51416":["México","Tejupilco",["San Lucas del Maíz (San Lucas)","La Joya de San Lucas","Salitre de San Lucas","Llano Grande (Llano Grande de San Lucas)","Piedra Ancha","El Salitre Segunda Sección"]],"51417":["México","Tejupilco",["Sauz de San Lucas (El Sauz)","El Platanal (El Platanal de San Lucas)","Agua Negra","Antonio de San Lucas del Maíz","Cuadrilla de los Martínez (Los Martínez)","Cuevillas","El Mamey de San Lucas","Fundadora de San Lucas del Maíz","Limón de San Lucas del Maíz","Los Melchores de San Lucas (Los Melchores)"]],"51418":["México","Tejupilco",["Tenería (Pueblo Nuevo)","Almoloya de las Granadas","Cerro Alto (Milpa Vieja)","Río Grande"]],"51422":["México","Tejupilco",["La Labor de Zaragoza","Cerro Gordo","El Limón de Ixtapan","El Rodeo","La Estancia de Ixtapan","Ocoyapan","Zapote del Ancón"]],"51423":["México","Tejupilco",["Arballo","Pantoja","Antimonio","Antimonio Pantoja","El Capire de Pantoja","Santiago Arizmendi (Arizmendi)"]],"51424":["México","Tejupilco",["Llano Grande","El Sauz Ocotepec (El Sauz)","Encinos Verdes","Las Ánimas","Rincón el Sauz Ocotepec"]],"51425":["México","Tejupilco",["Cerro del Chirimoyo","Cerro del Divisadero","El Zapote de Ixtapan (El Zapote)","Hacienda de Ixtapan","Juluapan (Juloapan)","Las Moras","Lodo Prieto","Los Nopales","Puerto de Jalpan (Jalpa)","Rincón Chiquito","San Francisco"]],"51426":["México","Tejupilco",["Puerto del Aire","Ilamos","La Guitarra","Las Juntas de Ixtapan","San Miguel Ixtapan"]],"51427":["México","Tejupilco",["El Carmen de Ixtapan","Tirados","Cuadrilla de López","El Aguacate de Monte de Dios","El Burrito (El Sauz)","Salitre de Acamuchitlán (El Salitre)","Las Juntas","Monte de Dios","Pinzán Morado","Plaza de Gallos","Salto Grande","San Mateo (San Mateo Ixtapan)"]],"51428":["México","Tejupilco",["Las Mesas de Ixtapan (Las Mesas)","Santa Rosa Rincón de Jaimes","El Potrero de Ixtapan (El Potrero)","La Florida (Kilómetro 5)","Barranca de Ixtapan","Campanario de Ixtapan (El Campanario)","Santa María de las Flores","Santa Rosa (Las Juntas)"]],"51430":["México","Tejupilco",["Bejucos","Benito Juárez (Lázaro Cárdenas del Río)","El Salto (El Salto Dos)","Las Lomas (Los Depósitos)"]],"51432":["México","Tejupilco",["Rincón del Guayabal","Cuadrilla del Molino","El Ciruelo","La Cañada","Las Mesas de los Capires (Las Mesas)","Rincón de Carboneras (Carboneras)"]],"51433":["México","Tejupilco",["La Cofradía (Los Mangos)","Acamuchitlán","Cerro de los Elizaldes","El Corupo","El Jumate","El Zapote de Acamuchitlán (El Zapote)","La Calera","La Mesa","Planes de la Cofradía (Los Planes)","Río Chiquito","Tejapan Limones (Tejapan)"]],"51434":["México","Tejupilco",["Coahuilotes","El Guayabo","El Naranjo Grande","La Bolsa","La Cuitacera","Las Anonas","Las Ilamas","Los Pinzanes (La Pinzanera)","Naranjo Chiquito","Paso de San Juan"]],"51435":["México","Tejupilco",["Paso del Guayabal (El Paso)","Barro Prieto","Paredes Prietas","Paso de la Parota"]],"51436":["México","Tejupilco",["Mesa de Gallos (El Llano)","La Palma Cuata (La Palma)","Potrero Grande"]],"51440":["México","Luvianos",["San Sebastián 1","Luvianos","San Sebastián (Rincón de San Sebastián)","Rincón de Alambre","Niños Héroes"]],"51442":["México","Luvianos",["Trojes","Arroyo Seco","Cerro del Venado","Cuadrilla de Benítez","Ojo de Agua","Rincón de Vargas","Toma de Agua"]],"51443":["México","Luvianos",["El Estanco","Puerto del Salitre","Calaveras","Capire","El Pie de la Loma","Jaquinicuil","Los Pinzanes"]],"51445":["México","Luvianos",["San Antonio Luvianos (San Antonio)","Cerro de la Culebra","Paso de la Arena"]],"51446":["México","Luvianos",["Caja de Agua","Cerro de Castelanes","Cerro del Agua","El Pueblito","Iglesia Vieja","Puerta de Golpe","Rincón de San Lucas"]],"51453":["México","Luvianos",["El Copalito","El Naranjito","El Puerto de la Sosa","El Reparo de Nanchititla (El Reparo)","El Rincón de Cagalaguas (Rincón los Mejías)","Hormigueros","Las Lajas","Las Palmas","Los Arrayanes (Los Arrayanes Verdes)","Los Bancos","Los Ocotes","Los Piñones (El Sauz)","Los Terreros","Plan de Chihuahua","Puerto de los Duraznos","Rincón de Arrayanes","Rincón de González"]],"51454":["México","Luvianos",["Cañadas de Nanchititla","Aguacatillo","Carrizal","Colcomeca","El Capire","Guayabos (El Guayabo)","La Laguna","Las Paredes","Los Bancos","Los Tejocotes","Majada de los Encinos (Majada de Encinos)","Monte Verde","Palo Verde","Palos Prietos","Peña Calva","Rincón de Martínez","Tequesquite (El Tequezquite)"]],"51455":["México","Luvianos",["El Cirare (Cirián de Hilar)","La Canoa","Las Parotas","Los Arrayanes","Los Llanitos","Los Tequereques","Mesa de los Caballos","Ojo de Agua-Palo Gordo","Palo Gordo","Sesteadero de Abajo","Sesteadero de Arriba","Solosúchil"]],"51456":["México","Luvianos",["Las Anonas","Caja de Agua","Calabazos (Las Pilas)","El Cerro","El Limón","El Plátano","El Pueblito","El Rodeo","La Angostura Dos","La Angostura Uno (Cerro de la Angostura Uno)","La Arboleda","La Camelina","La Mesa del Potrero Chiquito","La Toma","Los Pericones (Ranchería los Pericones)","Mesa de Nietos","Salitrillo","Sanguijuelas","El Sauz Palo Gordo","Tremesinos"]],"51457":["México","Luvianos",["La Estancia de Nanchititla (La Estancia)","Cacahuananche","Cuachinola","El Carrizal","El Huizache","El Jagüey","El Naranjo","El Tanque","Las Lajitas","Las Piñas","Los Arrayanes","Los Pinzanes","El Ojo de Agua","Piedra Colorada","Puerto de los Terreros","Puerto de los Zacatones","Sesteadero"]],"51458":["México","Luvianos",["Cuahuilotes (Cuajilotes)","Avellaneda","El Cascalote","El Manguito (La Parotilla)","El Salto de San Jerónimo","Jocoleche","Las Trojas","Lechuguillas","Los Curindales","Navarrete"]],"51459":["México","Luvianos",["El Barro","El Ranchito (El Limoncito)","Gabazos (El Bagaso)","Las Garzas (Potrerillos)"]],"51462":["México","Luvianos",["Rincón de Rodríguez","Carbajales","Corral Nuevo","Cruz de Piedra","El Capire de Acatitlán","El Limón","El Mamey Acatitlán","Jocoal","La Mesa","La Palma","La Unidad (Los Ciruelos)","Mango Solo","Rancho Viejo","Santa Cruz","El Salitre Estancia Grande"]],"51463":["México","Luvianos",["San Juan Acatitlán (Acatitlán)","Alborejo (Puerto Alborejo)","Corral del Barro","Cuadrilla de Sánchez","El Aguacate","El Naranjo de San Isidro (El Naranjo Primero)","Hilamache","Puerto del Higo","Rincón del Hilamache","Rincón del Naranjo la Presa","Salitre del Puente (Puente del Salitre)","Tres Encinos"]],"51464":["México","Luvianos",["Estancia Grande (San José Estancia Grande)","Puerto el Capulín","Santa Rosa Estancia Grande"]],"51465":["México","Luvianos",["San Simón Piedra Grande (San Simón)","Hermiltepec (Peña Blanca)","El Crucillo","El Manguito","El Rincón Piedra Grande","Jalpan","La Candelaria","La Minita","Magadán","Paso del Agua (Cristo Rey)","Piedra Grande","Salitre Piedra Grande","Santa Rosa Hermiltepec","Mesa de los Espinos (Mesa de las Escobas)"]],"51466":["México","Luvianos",["El Tecuán","La Chaqueta","La Laguna","Potrero de Palmarillos"]],"51467":["México","Luvianos",["Buenavista","El Brasil","El Pueblito","La Parota","La Yerbabuena","Los Bancos","Los Pozos","Mesa del Capulín (Mesa de los Nanches)","Pedernales","Potrero Vallecitos (El Potrero)","Pungarancho","San Nicolás","Vallecitos de Hermiltepec (Vallecito)"]],"51468":["México","Luvianos",["Agua Colorada","Arrayán","Cañada del Campanario","Chirimoya","Ciprianes","Cruz de Clavos","El Campanario","El Cirián de Hermiltepec","El Granjen","Huiztepec","Rincón Cruz de Clavos","Rincón de Ciprianes"]],"51470":["México","San Simón de Guerrero",["San Simón de Guerrero","San Pedro (El Espinal)","Cruz Verde","San José (Barrio Tecolote)","La Fragua","Santa Cruz","Santa Rosa (La Gallinada)"]],"51476":["México","San Simón de Guerrero",["Del Monte"]],"51479":["México","San Simón de Guerrero",["Estancia Vieja (San José la Estancia)","Los Berros Cuentla","Mina de Agua"]],"51480":["México","San Simón de Guerrero",["La Rueda","San Diego Cuentla (Llano Grande)","San Gabriel Cuentla","Titipac Cuentla (Titipac)","La Rinconada","Peña Redonda","Rincón de los Trigos"]],"51483":["México","San Simón de Guerrero",["Rancho Viejo Cuentla (Rancho Viejo)","La Sierrita","Yerbabuena"]],"51484":["México","San Simón de Guerrero",["El Mango Cuentla (El Mango)","El Zapote","Guardarraya"]],"51485":["México","San Simón de Guerrero",["El Jocoyol Cuentla (Jocoyoles)","El Momustle","La Cumbre"]],"51500":["México","Amatepec",["Amatepec"]],"51510":["México","Amatepec",["Rincón de la Cofradía","San Martín","El Aguacate (El Aguacate San Martín)"]],"51513":["México","Amatepec",["Chapuluapan","Rincón de San Simón","Corral de Piedra","Cerro de Tlacotepec (Tlacotepec)","Coyol de San Simón","Encinal Verde"]],"51514":["México","Amatepec",["Los Guajes","San Miguel (San Miguel Zinacausto)","Coahuilotes (Los Coahuilotes)","El Malpaso","Cerro de Santiago","Güijas Blancas","El Mango Piedras Anchas"]],"51515":["México","Amatepec",["El Veladero","La Mora","El Puerto","Joya de la Venta"]],"51516":["México","Amatepec",["El Panteón de San Felipe de Jesús","La Carrera","Los Encinos","Los Timbres","El Monteal (Barranca Papaloapan)","Las Joyas","San Felipe de Jesús","Puente Viejo"]],"51517":["México","Amatepec",["San Simón (San Simón Zozocoltepec)","Tepehuajes Uno (Tepehuajes de Arriba)","Tepehuajes (Tepehuajes de Abajo)","La Parota (La Parota Tepehuajes)"]],"51518":["México","Amatepec",["El Llano"]],"51523":["México","Amatepec",["Cerro de las Ánimas (El Cerro de las Ánimas)","El Sitio","Pueblo Nuevo (San Lucas Pueblo Nuevo)","Cerro de las Ánimas-El Manguito","San Marcos"]],"51524":["México","Amatepec",["Tepehuastitlán","Salitre de López"]],"51525":["México","Amatepec",["Palmarillos","Aguacatitlán (La Carreta)","Dolores (Hacienda Dolores)","El Rancho","El Fresno","Salitre Palmarillos","Los Sabinos","Charco Hondo (El Tlacuache)"]],"51526":["México","Amatepec",["Rincón de Esmeraldas","Ayuquila","Las Latas (Ayuquila)","San Francisco de los Pinzanes","La Chupa Rosa","Los Órganos","Las Pailas","La Rayuela","Barranca de Esmeraldas (La Güila)"]],"51527":["México","Amatepec",["Barranca del Mamey","Crucero Cerro del Campo","Cuadrilla del Naranjo (Rincón del Naranjo)","Cuadrilla Nueva (La Presa)","El Zapote","Puente del Rodeo","Los Timbres","La Cofradía","Cerro del Campo","Santiago","El Ortigo","Peña del Cuervo","Escuela Vieja","Acatempan","Cuadrilla Nueva","Barrio de la Uva"]],"51530":["México","Amatepec",["Palmar Chico","Salitre Santa Bárbara (Santa Bárbara)","El Conejo (Conejo Viejo)","Aviación (Campo de Aviación)","La Chaqueta","El Pantalón","El Convento"]],"51533":["México","Amatepec",["Los Ajoques","El Tlapanco","Meyuca","Cerro del Coyol","Barranca del Coyol","San Juan Tizapán (La Haciendita)","Cristo Rey (Guacamayas)"]],"51534":["México","Amatepec",["Matuz Puerto del Rodeo","San Antonio Matuz","La Palma","Las Ceibas","Potrerillos (Potrerillos Matuz)","Pinzanes Matuz","El Arrayán"]],"51535":["México","Amatepec",["Cuadrilla de López","El Tamarindo","Guayabillos"]],"51536":["México","Amatepec",["Corral Viejo","Santa Bárbara","Mango Matuz","Buenavista"]],"51537":["México","Amatepec",["El Mamey","Huixtitla","Amadores (Los Amador)","Cincuenta Arrobas","Quimichatenco (Barranca de Quimichatenco)","El Zapote (El Zapote López)","El Zapote Cincuenta Arrobas (El Zapote)","San José (San José del Palmar)","Barranca de Gallegos"]],"51540":["México","Amatepec",["El Pino","Tierra Azul","Platanal","Los Colorines","Los Espinos","El Consuelo","Puerto de la Uva","El Paraje"]],"51543":["México","Amatepec",["Tlalchichilpan","El Rodeo"]],"51544":["México","Amatepec",["Sumpancle","La Goleta","Zacatones"]],"51550":["México","Tlatlaya",["Tlatlaya"]],"51553":["México","Tlatlaya",["La Cueva","Loma Larga","Peña del Agua","Piedra Ancha","Puerto Frío","Teopazul (Teopazul el Encinal)","Piedra Ancha II","La Unión","Coatepec (Coatepequito)","Miraveles","Dieciocho de Marzo","El Terroncillo","San Lucas"]],"51554":["México","Tlatlaya",["Corral de Piedra Dos (Corral de Piedra)","Juntas del Paso Topilar","Arenal","Tecomatlán","Cerro del Morado","El Revelado"]],"51555":["México","Tlatlaya",["El Potrero","La Laguna Puerto de la Arena","Puerto de la Arena","Plan de la Cuadrilla"]],"51556":["México","Tlatlaya",["Cuadrilla de los Sotero","Juntas del Río Limón","San Mateo (San Mateo Guayatenco)","El Limón","El Mango","Cuadrilla de Gutiérrez"]],"51557":["México","Tlatlaya",["Los Ocotes","San Juan Tetitlán","Benito Juárez"]],"51558":["México","Tlatlaya",["Barriales","La Cofradía","Pueblo Nuevo"]],"51559":["México","Tlatlaya",["Corral Parota (Tepehuastitlán)","La Guacamaya","Mazatitla","Cuadrilla de Flores","Santa Cruz","Santa María"]],"51560":["México","Tlatlaya",["La Cubata","Limón Terrero","Azúchil"]],"51564":["México","Tlatlaya",["El Poroche","El Tiquimil","Los Bautistas (Cerro de los Bautistas)","Las Juntas de Azúchil"]],"51565":["México","Tlatlaya",["El Devanador","Vuelta del Río"]],"51566":["México","Tlatlaya",["Coahuilotes (Pueblo Nuevo)","El Naranjito (Naranjito del Paso)","Ranchos Nuevos","El Zapote (El Zapote San Antonio del Rosario)","Cacahuananche"]],"51568":["México","Tlatlaya",["La Lagunilla"]],"51569":["México","Tlatlaya",["Agua Fría","La Víbora","Las Juntas (Las Juntas del Paso)","Paso de Jaquinicuil","El Naranjito","El Reparo","El Ciruelo","Los Limones"]],"51570":["México","Tlatlaya",["Santa Ana Zicatecoyan","Tierra Blanca"]],"51572":["México","Tlatlaya",["Barranca de las Flores","Chachalacatenco","El Alambique","Peña Colorada","Pinzán Morado","Plan del Alambique"]],"51573":["México","Tlatlaya",["El Montón","El Tamarindo","El Toroal","San Juan Corral","La Parota"]],"51574":["México","Tlatlaya",["Los Hornos","Pinzán Morado (Cerro Blanco)","Río Topilar (Topilar)"]],"51575":["México","Tlatlaya",["Charco del Lagarto","El Manguito","Peña del Órgano"]],"51576":["México","Tlatlaya",["Cuadrilla Nueva","Juntas de Santa Ana Zicatecoyan","El Zopilote","Moctezuma","Rancho Cuá"]],"51577":["México","Tlatlaya",["Amacuatitla","Puerto Minatitlán","Cruz del Norte","El Gavilán","Puerto Seco"]],"51578":["México","Tlatlaya",["Cerro de Aguacatepec","El Mango","Corral de Piedra","Salitrillo","Rincón del Aguacate","Salitre Grande","La Alcantarilla"]],"51579":["México","Tlatlaya",["El Suchual de Santa Ana (El Suchual)","San Felipe Tepehuastitlán","Pie del Cerro","Tejupilquito","La Cofradía","Cuadrilla del Cirián (Cirián Grande)"]],"51580":["México","Tlatlaya",["El Limo","San Francisco de Asís (San Francisco)","Tlacocuspan (Tlacocuspan Santa Cruz)"]],"51582":["México","Tlatlaya",["Palmar Grande"]],"51583":["México","Tlatlaya",["Macuatitla","Pie del Cerro San Vicente","Palma Torcida"]],"51584":["México","Tlatlaya",["El Salitre Ojo de Agua","Cuadrilla Nueva","Ancón de los Curieles","El Higo Prieto"]],"51585":["México","Tlatlaya",["San Pedro Limón"]],"51586":["México","Tlatlaya",["El Naranjo Palmar Grande","Palos Verdes"]],"51587":["México","Tlatlaya",["El Cascalote","Cirián Grande","El Guayabo","El Llano","Huixtitla","Peña Blanca","Rancho Viejo","Mayaltepec"]],"51588":["México","Tlatlaya",["El Guitarratel","El Sauz","Puerto de los Martínez","Las Esmeraldas (Puerto del Órgano)","Las Esmeraldas"]],"51590":["México","Tlatlaya",["Rincón Grande"]],"51598":["México","Tlatlaya",["Las Juntas","Palos Altos","San Antonio del Rosario","El Naranjo","Nuevo Copaltepec","El Temblor"]],"51599":["México","Tlatlaya",["La Parota","Ancón de la Presa"]],"51600":["México","Sultepec",["Sultepec de Pedro Ascencio de Alquisiras"]],"51603":["México","Sultepec",["Capula"]],"51604":["México","Sultepec",["Hacienda de Real de Abajo (Santa Lucía)"]],"51605":["México","Sultepec",["Diego Sánchez","La Ciénega"]],"51606":["México","Sultepec",["Santa Cruz (Santa Cruz Texcalapa)","Santo Tomás de las Flores (Santo Tomás)"]],"51607":["México","Sultepec",["La Albarrada","La Unión"]],"51610":["México","Sultepec",["Sultepequito","San Isidro Xochitla","La Laguna","San Miguel Terrero"]],"51613":["México","Sultepec",["Santa Anita","Pepechuca","San Hipólito Zacatales","Sultepequito"]],"51614":["México","Sultepec",["Las Peñas","El Rincón del Cristo (Rinconada del Cristo)","El Cristo","El Momoxtle"]],"51620":["México","Sultepec",["Aserradero Viejo","Puerto Frío","La Troja Vieja","Los Epazotes"]],"51623":["México","Sultepec",["Puentecillas","Las Mesas","Cuatro Cruces"]],"51624":["México","Sultepec",["La Virgen","San José el Potrero","Trojes","Segunda Manzana de Cuatro Cruces"]],"51633":["México","Sultepec",["Manial de Guadalupe de Abajo","Manial de Guadalupe de Arriba","Cruz de Cedro"]],"51634":["México","Sultepec",["Mextepec","San Miguelito","El Ranchito","San Francisco de Asís"]],"51635":["México","Sultepec",["El Potrero (Potrero de Guadalupe)"]],"51636":["México","Sultepec",["Potzontepec","El Calvarito"]],"51637":["México","Sultepec",["El Teamate","Salayatla","Salinas","Atzumpa","Rincón de los Aguilares"]],"51640":["México","Sultepec",["San Pedro Hueyahualco"]],"51644":["México","Sultepec",["Jalpan (Jalpa)","El Huizache"]],"51645":["México","Sultepec",["San Miguel Totolmaloya","Cojaltitla","Tenanguillo de las Peñas","Laguna Verde"]],"51646":["México","Sultepec",["El Naranjo"]],"51647":["México","Sultepec",["Puente Mocho","San José Xochitla"]],"51650":["México","Sultepec",["Coquillo","Metlaltepec","Filo de los Amates","Las Joyas"]],"51653":["México","Sultepec",["Laguna Seca","Capulatengo"]],"51654":["México","Sultepec",["San Nicolás del Cobre (San Nicolás)","Tehuilotepec"]],"51655":["México","Sultepec",["El Puerto del Teamate (Puerto de las Majadas)"]],"51670":["México","Texcaltitlán",["Santa María","Texcaltitlán","San Miguel","Acatitlán"]],"51673":["México","Texcaltitlán",["Tlacotepec","Venta Morales ( El Pedregal )","Palo Amarillo","El Agostadero"]],"51674":["México","Texcaltitlán",["Palmillas","Ojo de Agua","Venta Morales (La Laguna)"]],"51675":["México","Texcaltitlán",["San Agustín","El Chapaneal","Gavia Chica ( Rincón )","Los Lirios","Las Tablas (Las Tablas San José)","San José"]],"51676":["México","Texcaltitlán",["El Salto","Texcapilla","Llano Grande","Nueva Santa María"]],"51693":["México","Texcaltitlán",["Jesús del Monte","Yuytepec"]],"51694":["México","Texcaltitlán",["Agua del Trébol","Las Paredes"]],"51695":["México","Texcaltitlán",["Hueyatenco","Carbajal","Noxtepec","Rastrojo Largo"]],"51696":["México","Texcaltitlán",["Chiquiuntepec (Chiquintepec)"]],"51697":["México","Texcaltitlán",["San Francisco","Arroyo Seco"]],"51700":["México","Coatepec Harinas",["Coatepec Harinas","Primera de San Miguel (La Punta)","Segunda de Analco (La Presa)"]],"51704":["México","Coatepec Harinas",["Segunda de San Miguel (El Cerrito)"]],"51705":["México","Coatepec Harinas",["Primera de Zacanguillo (Santo Niño Doctor)"]],"51713":["México","Coatepec Harinas",["Guadalupe"]],"51714":["México","Coatepec Harinas",["Cochisquila","Plan de San Francisco","Cuentla"]],"51715":["México","Coatepec Harinas",["Primera de Analco"]],"51716":["México","Coatepec Harinas",["Acuitlapilco","El Potrero"]],"51720":["México","Coatepec Harinas",["San José del Progreso (San José)","Loma de Acuitlapilco","Santo Niño","San Martín el Salto","Zacatones (San Felipe de Jesús)"]],"51723":["México","Coatepec Harinas",["La Providencia","El Telar","Potrero Redondo","Agua Bendita","El Picacho","La Conchita","Las Trojes"]],"51724":["México","Coatepec Harinas",["Segunda del Monte (La Presa)","Primera del Monte (La Presa)","Primera de Santa Ana","Segunda de Zacanguillo","Segunda de Santa Ana"]],"51725":["México","Coatepec Harinas",["Las Jaras"]],"51726":["México","Coatepec Harinas",["Agua Amarga","San Fernando","Los Fresnos"]],"51727":["México","Coatepec Harinas",["Tecolotepec","Teocotitla","El Potrerito (El Potrero)","Capulín Redondo","Huayanalco","Piedras Anchas (Primera del Monte)","La Rosa"]],"51730":["México","Coatepec Harinas",["Puerta del Carmen","Llano Grande"]],"51733":["México","Coatepec Harinas",["Meyuca de Morelos (Meyuca)","Baja de Laja Azul","Alta de Laja Azul"]],"51734":["México","Coatepec Harinas",["El Reynoso","San Luis (Colonia Hidalgo)","El Cedrito"]],"51735":["México","Coatepec Harinas",["Adolfo López Mateos","La Cercada"]],"51750":["México","Coatepec Harinas",["Chiltepec de Hidalgo","Las Vueltas","La Laguna"]],"51753":["México","Coatepec Harinas",["Monte de las Vueltas","La Galera"]],"51754":["México","Coatepec Harinas",["Ixtlahuaca de Villada","Cruz de Piedra","Las Mesas","San Pedro"]],"51760":["México","Villa Guerrero",["San Francisco","Villa Guerrero","15 de Mayo","Santa Cecilia"]],"51765":["México","Villa Guerrero",["Buenavista","San Felipe","Jesús Carranza (Rancho de Jesús)","El Islote","Ejido de San Mateo Coapexco","Coxcacoaco"]],"51766":["México","Villa Guerrero",["El Progreso Hidalgo"]],"51767":["México","Villa Guerrero",["La Finca","Potrero Nuevo","Ejido de la Finca"]],"51773":["México","Villa Guerrero",["El Venturero Santa María Aranzazú","San Diego","Cruz Vidriada"]],"51775":["México","Villa Guerrero",["Santa María Aranzazú (Santa María)","La Joya"]],"51776":["México","Villa Guerrero",["San Miguel","San Lucas"]],"51777":["México","Villa Guerrero",["San Bartolomé (San Bartolo)","San José","El Moral","Los Ranchos de San José","Cuajimalpa (Los Cuervos)","Zanjillas San Bartolomé"]],"51783":["México","Villa Guerrero",["San Mateo Coapexco","Santiago Oxtotitlán","Zacango","Loma de Zacango (El Venturero)"]],"51784":["México","Villa Guerrero",["Totolmajac","El Carmen","El Izote","San Pedro Buenos Aires (San Pedro)"]],"51785":["México","Villa Guerrero",["Porfirio Díaz"]],"51786":["México","Villa Guerrero",["San Gaspar","La Loma de la Concepción (La Loma)","Matlazinca","Tequimilpa","El Peñón","Potrero de la Sierra"]],"51800":["México","Zacualpan",["Paraje el Cuetzillo","Zacualpan","Santiago","Los Zapotes (Barrio San José)","Tlapexco"]],"51810":["México","Zacualpan",["Huitzoltepec"]],"51813":["México","Zacualpan",["Ayotuxco"]],"51814":["México","Zacualpan",["San Juan","Coloxtitlán","Tetzicapan (Texicapan)"]],"51815":["México","Zacualpan",["Gama de la Paz","Zotzocola","El Sitio","San Jerónimo"]],"51816":["México","Zacualpan",["El Fresno","El Salto","El Durazno"]],"51817":["México","Zacualpan",["Tres Cruces","Río Florido 2da. Sección","El Colorín","Río Florido 1ra. Sección"]],"51820":["México","Zacualpan",["Piedra Parada","Tepextitla 2da. Sección"]],"51825":["México","Zacualpan",["El Despoblado","Agua Dulce","Los Ejidos"]],"51826":["México","Zacualpan",["La Luz","Las Huertas","Apetlahuacan"]],"51827":["México","Zacualpan",["El Cortijo","Los Planes Vista Hermosa","Zacualpilla","Tepextitla 1ra. Sección"]],"51850":["México","Zacualpan",["Los Barriales","Hueytecoxco","Tres Cruces","Mamatla","El Coyol"]],"51854":["México","Zacualpan",["Memetla","Cruz de Quiote","La Mora","Velixtla"]],"51855":["México","Zacualpan",["Teocaltzingo","El Verdecillo","La Trinidad","Yolotepec"]],"51856":["México","Zacualpan",["Ixtayotla","Coronas"]],"51857":["México","Zacualpan",["San Antonio Amealco","Calatepec","Huaxtitla","La Cofradía"]],"51860":["México","Almoloya de Alquisiras",["Almoloya de Alquisiras","Jaltepec de Arriba","Cuarta Manzana","Cerro de Tlapexco (Segunda Manzana)"]],"51863":["México","Almoloya de Alquisiras",["La Unión Riva Palacio","Totoltepec de la Paz","Cerro del Guayabo","La Barranca","La Guadalupana","Loma Larga","Totoltepec de Arriba"]],"51864":["México","Almoloya de Alquisiras",["San Andrés Tepetitlán","Plutarco González (Higueras)","Capulmanca"]],"51865":["México","Almoloya de Alquisiras",["Quinta Manzana","Ahuacatitlán (Aguacatitlán)"]],"51866":["México","Almoloya de Alquisiras",["Agua Fría","Tepehuajes","Las Mesas","Los Ranchos","Mesa del Río"]],"51867":["México","Almoloya de Alquisiras",["Progreso los Hernández (Colonia los Hernández)","San Antonio Pachuquilla","Buenos Aires","Llano de las Casas","San José Tizates (Tizates)","Vista Hermosa"]],"51870":["México","Almoloya de Alquisiras",["Cuauhtenco"]],"51874":["México","Almoloya de Alquisiras",["Sexta Manzana","Los Pinos","El Mirador","La Lobera"]],"51875":["México","Almoloya de Alquisiras",["Plan de Vigas","Yerbabuena"]],"51880":["México","Almoloya de Alquisiras",["Los Pérez","Aquiapan"]],"51883":["México","Almoloya de Alquisiras",["Triguillos","Cuevillas"]],"51900":["México","Ixtapan de la Sal",["Ixtapan de la Sal"]],"51904":["México","Ixtapan de la Sal",["Santa Ana","San Pedro"]],"51905":["México","Ixtapan de la Sal",["Santa Catarina","10 de Agosto","Revolución"]],"51906":["México","Ixtapan de la Sal",["Los Cedros","INFONAVIT","5 de Febrero","3 de Mayo"]],"51907":["México","Ixtapan de la Sal",["San Gaspar","Bugambilias","Ixtapita"]],"51910":["México","Ixtapan de la Sal",["El Abrojo"]],"51915":["México","Ixtapan de la Sal",["Los Naranjos","Juárez"]],"51916":["México","Ixtapan de la Sal",["Ahuacatitlán","San José del Arenal","San Miguel Laderas","Yerbas Buenas","Plan de San Miguel","El Rincón de Dios Yerbas Buenas","San Pablo"]],"51917":["México","Ixtapan de la Sal",["San Diego Alcalá","Llano de la Unión","Santa Ana Xochuca","Llano de San Diego","Palo Blanco","El Progreso"]],"51920":["México","Ixtapan de la Sal",["Tlacochaca","San Pedro Tlacochaca","San Andrés","Portezuelos"]],"51923":["México","Ixtapan de la Sal",["Yautepec"]],"51924":["México","Ixtapan de la Sal",["El Salitre","Rancho San Diego","Residencial Cipres"]],"51930":["México","Ixtapan de la Sal",["Malinaltenango"]],"51933":["México","Ixtapan de la Sal",["Tecomatepec","San Alejo","Puerta Grande","El Refugio","El Arenal de las Ollas"]],"51936":["México","Ixtapan de la Sal",["Coaxusco"]],"51937":["México","Ixtapan de la Sal",["Mesón Nuevo"]],"51950":["México","Tonatico",["Tonatico Centro","Santa María Norte","San Sebastián","San Gaspar","Santa María Sur","San Felipe","Portón de Sueño"]],"51953":["México","Tonatico",["Paso de San Juan"]],"51954":["México","Tonatico",["La Comunidad"]],"51955":["México","Tonatico",["San Miguel"]],"51956":["México","Tonatico",["El Rincón","El Trapiche"]],"51959":["México","Tonatico",["Los Amates (San José de los Amates)"]],"51960":["México","Tonatico",["Tlacopan"]],"51963":["México","Tonatico",["La Audiencia","San Bartolo"]],"51964":["México","Tonatico",["Salinas","El Terrero"]],"51970":["México","Tonatico",["El Zapote"]],"51973":["México","Tonatico",["La Puerta de Santiago"]],"51974":["México","Tonatico",["Ojo de Agua","Colixtlahuacán"]],"51977":["México","Tonatico",["La Vega"]],"51980":["México","Zumpahuacán",["Santa Ana","San Mateo","Zumpahuacan","San Juan","San Pedro","San Agustín","San Miguel","La Ascensión","La Cabecera"]],"51984":["México","Zumpahuacán",["San Nicolás Palo Dulce","Guadalupe Ahuacatlán"]],"51985":["México","Zumpahuacán",["Llano del Copal","Santiaguito"]],"51986":["México","Zumpahuacán",["San Pablo Tejalpa","Santa Catarina","San Miguel Ateopa"]],"51987":["México","Zumpahuacán",["San José Tecontla","San Antonio Guadalupe"]],"51988":["México","Zumpahuacán",["Guadalupe Tlapizalco"]],"51989":["México","Zumpahuacán",["Santa Cruz de los Pilares"]],"51990":["México","Zumpahuacán",["San Gaspar"]],"51994":["México","Zumpahuacán",["San Mateo Despoblado","Amolonca","Santa María la Asunción"]],"51995":["México","Zumpahuacán",["Chiapa San Isidro","Guadalupe Chiltamalco","Santa Ana Despoblado","San Pedro Guadalupe (Despoblado)","Santa Cruz Atempa"]],"51996":["México","Zumpahuacán",["Ahuatzingo"]],"51997":["México","Zumpahuacán",["El Zapote","Guadalupe Victoria","El Tamarindo"]]}